fmsfdata/__init__.py
fmsfdata/converter.py
fmsfdata/datastore/__init__.py
fmsfdata/datastore/_store.py
fmsfdata/datastore/_table.py
fmsfdata/datastore/_table_key.py
fmsfdata/datastore/_table_row.py
fmsfdata/exporter.py
fmsfdata/identifier.py
fmsfdata/normaliser.py
fmsfdata/schema/__init__.py
fmsfdata/schema/_data.py
fmsfdata/schema/_proxy.py
fmsfdata/schema/_types.py
fmsfdata/schema/erd/__init__.py
fmsfdata/schema/erd/templates/erd.dot
fmsfdata/schema/parser/__init__.py
fmsfdata/settings.py
fmsfdata/standardiser.py
fmsfdata/stream_parser/__init__.py
fmsfdata/stream_parser/checks.py
fmsfdata/stream_parser/collectors.py
fmsfdata/stream_parser/events.py
fmsfdata/stream_parser/filters/__init__.py
fmsfdata/stream_parser/filters/column_headers.py
fmsfdata/stream_parser/filters/context.py
fmsfdata/stream_parser/filters/generic.py
fmsfdata/stream_parser/filters/types.py
fmsfdata/stream_parser/function_helpers.py
fmsfdata/stream_parser/functions.py
fmsfdata/stream_parser/parser/__init__.py
fmsfdata/stream_parser/parser/csv.py
fmsfdata/stream_parser/parser/openpyxl.py
fmsfdata/stream_parser/parser/xml.py
fmsfdata/stream_parser/stream.py
fmsfdata/stream_parser/types.py
fmsfdata-3.1.0.dist-info/METADATA
fmsfdata-3.1.0.dist-info/WHEEL
fmsfdata-3.1.0.dist-info/RECORD
